Workbook

Sheet 预算表 
A2: 培训办班项目收支预算表
A3: 编制部门：（公章） | D3: 45309 | G3: 单位：元
A4: 项目名称 | B4: 上海外高桥造船有限公司班组长能力提升培训班 | F4: 项目类型 | G4: 线下
A5: 培训人数 | B5: 50 | C5: 收费标准 | D5: =G5/B5 -> 1930 | F5: 收费合计 | G5: 96500
A6: 培训天数 | B6: 32课时 | E6: 4天 | F6: 项目负责人 | G6: 郭小铭
A7: 序号 | B7: 收入预算明细 | F7: 金额 | G7: 备注
A8: 1 | B8: 培训费收入 | F8: =G5 -> 96500
B10: 收入合计
A11: 序号 | B11: 支出预算明细 | E11: 测算依据 | F11: 金额 | G11: 备注
A12: 1 | B12: 场地费 | E12: 800元/天*1天 | F12: =800*1 -> 800 | G12: 必须按实际需要填列，严格控制在合理成本范围内
A13: 2 | B13: 授课讲师费（专家） | E13: 2000元/课时*8课时*1人 | F13: =8*2000 -> 16000
A14: 3 | B14: 授课讲师费（讲师） | E14: 1000元/课时*24课时*1人 | F14: =24*1000 -> 24000
A15: 4 | B15: 伙食费 | E15: 30元/人次*50人*4次 | F15: =30*50*4 -> 6000
A16: 5 | B16: 茶歇 | E16: 15元/人次*50人*8次 | F16: =15*50*8 -> 6000
A17: 6 | B17: 劳务费 | E17: 500元/人天*4天*3人 | F17: =500*4*3 -> 6000
A18: 7 | B18: 学校管理费 | E18: 收入的15% | F18: =F8*0.15 -> 14475
A19: 8 | B19: 学员手册等印刷费 | E19: 100元/人*50人 | F19: 5000
B23: 支出合计 | F23: =SUM(F12:F22) -> 78275
B24: 结 余 | F24: =G5-F23 -> 18225
A26: 财务处审核： | E26: 项目负责人审核： | G26: 制表人：
A28: 注：项目结束后及时到财务处办理结题手续

Sheet 测算表
A1: 成本测算表（上海劳模学院）
A2: 项目名称 | B2: 班组长能力提升培训项目（第1期） | E2: 培训形式 | F2: 业余制
A3: 班级人数 | B3: 50 | C3: 培训收费 | D3: =F3/B3 -> 1930 | E3: 合计收入 | F3: 96500
A4: 培训课时 | B4: 32 | C4: 教师配备 | D4: 在职：8人 | E4: 班主任 | F4: 3人
B5: 成本测算内容 | F5: 金 额
A6: 1 | B6: ='预算表 '!B12&" "&'预算表 '!E12 -> 场地费 800元/天*1天 | F6: ='预算表 '!F12 -> 800
A7: 2 | B7: ='预算表 '!B13&" "&'预算表 '!E13 -> 授课讲师费（专家） 2000元/课时*8课时*1人 | F7: ='预算表 '!F13 -> 16000
A8: 3 | B8: ='预算表 '!B14&" "&'预算表 '!E14 -> 授课讲师费（讲师） 1000元/课时*24课时*1人 | F8: ='预算表 '!F14 -> 24000
A9: 4 | B9: ='预算表 '!B15&" "&'预算表 '!E15 -> 伙食费 30元/人次*50人*4次 | F9: ='预算表 '!F15 -> 6000
A10: 5 | B10: ='预算表 '!B16&" "&'预算表 '!E16 -> 茶歇 15元/人次*50人*8次 | F10: ='预算表 '!F16 -> 6000
A11: 6 | B11: ='预算表 '!B17&" "&'预算表 '!E17 -> 劳务费 500元/人天*4天*3人 | F11: ='预算表 '!F17 -> 6000
A12: 7 | B12: ='预算表 '!B18&" "&'预算表 '!E18 -> 学校管理费 收入的15% | F12: ='预算表 '!F18 -> 14475
A13: 8 | B13: ='预算表 '!B19&" "&'预算表 '!E19 -> 学员手册等印刷费 100元/人*50人 | F13: ='预算表 '!F19 -> 5000
A14: 9 | B14: ='预算表 '!E20&" "&'预算表 '!E20 | F14: =SUM(F3)-SUM(F6:F13) -> 18225
A15: 成本合计 | F15: =SUM(F6:F14) -> 96500
A16: 课时标准成本=总收入÷人数÷课时=167000/36/28=165.67元/人·课时

Sheet 测算表 (最终)
A1: 成本测算表（上海劳模学院）
A2: 项目名称 | B2: 班组长能力提升培训项目（第1期） | E2: 培训形式 | F2: 业余制
A3: 班级人数 | B3: 50 | C3: 培训收费 | D3: =F3/B3 -> 1930 | E3: 合计收入 | F3: 96500
A4: 培训课时 | B4: 32 | C4: 教师配备 | D4: 在职：12人 | E4: 班主任 | F4: 3人
B5: 成本测算内容 | F5: 金 额
A6: 1 | B6: 场地费 2500元/天*4天 | F6: 10000
A7: 2 | B7: 授课讲师费（专家） 2000元/课时*8课时*1人 | F7: 16000
A8: 3 | B8: 授课讲师费（讲师） 1000元/课时*24课时*1人 | F8: 24000
A9: 4 | B9: 伙食费 35元/人次*50人*4次 | F9: 7000
A10: 5 | B10: 茶歇 20元/人次*50人*8次 | F10: 8000
A11: 6 | B11: 劳务费 800元/人天*4天*3人 | F11: 9600
A12: 7 | B12: 学校管理费 收入的15% | F12: 14475
A13: 8 | B13: 学员手册等印刷费 148.5元/人*50人 | F13: 7425
A14: 9 | B14: ='预算表 '!E20&" "&'预算表 '!E20 | F14: =SUM(F3)-SUM(F6:F13) -> 0
A15: 成本合计 | F15: =SUM(F6:F14) -> 96500
A16: 课时标准成本=总收入÷人数÷课时=96500/50/32=60.3125元/人·课时
